LICENSE
MANIFEST.in
README.rst
setup.py
rdate/__init__.py
rlib_date.egg-info/PKG-INFO
rlib_date.egg-info/SOURCES.txt
rlib_date.egg-info/dependency_links.txt
rlib_date.egg-info/not-zip-safe
rlib_date.egg-info/top_level.txt