Metadata-Version: 1.1
Name: rlib-date
Version: 0.1
Summary: Alternative to standard datetime library.
Home-page: https://github.com/t5w5h5/rdate
Author: t5w5h5
Author-email: t5w5h5@gmail.com
License: MIT
Download-URL: https://github.com/t5w5h5/rdate/archive/0.1.tar.gz
Keywords: date,time,datetime
Platform: any
Classifier: Development Status :: 3 - Alpha
Classifier: Intended Audience :: Developers
Classifier: License :: OSI Approved :: MIT License
Classifier: Natural Language :: English
Classifier: Operating System :: OS Independent
Classifier: Programming Language :: Python :: 3.6
Classifier: Programming Language :: Python
Classifier: Topic :: Software Development :: Libraries :: Python Modules
